src/clean_folder_RSA/__init__.py
src/clean_folder_RSA/clean.py
clean_folder_RSA-0.0.4.dist-info/LICENSE
clean_folder_RSA-0.0.4.dist-info/METADATA
clean_folder_RSA-0.0.4.dist-info/WHEEL
clean_folder_RSA-0.0.4.dist-info/entry_points.txt
clean_folder_RSA-0.0.4.dist-info/top_level.txt
clean_folder_RSA-0.0.4.dist-info/RECORD
