Metadata-Version: 2.1
Name: clean-folder-RSA
Version: 0.0.4
Summary: Home work 7 . Clean folder script
Home-page: https://github.com/My-codes-future/project_dz7
Author: Sergiy Rusetskiy
Author-email: rusetskit1974s@ukr.net
Classifier: Programming Language :: Python :: 3
Classifier: License :: OSI Approved :: MIT License
Classifier: Operating System :: OS Independent
License-File: LICENSE
